dupr_api/__init__.py
dupr_api/client.py
dupr_api/exceptions.py
dupr_api/api/__init__.py
dupr_api/api/admin.py
dupr_api/api/base.py
dupr_api/api/brackets.py
dupr_api/api/clubs.py
dupr_api/api/events.py
dupr_api/api/matches.py
dupr_api/api/players.py
dupr_api/api/user.py
dupr_api_client-1.0.1.dist-info/licenses/LICENSE
dupr_api_client-1.0.1.dist-info/METADATA
dupr_api_client-1.0.1.dist-info/WHEEL
dupr_api_client-1.0.1.dist-info/top_level.txt
dupr_api_client-1.0.1.dist-info/RECORD
