Metadata-Version: 2.4
Name: dupr-api-client
Version: 1.0.1
Summary: A comprehensive Python client library for the DUPR (Dynamic Universal Pickleball Rating) API
Home-page: https://github.com/offsetkeyz/dupr-api-client
Author: offsetkeyz
Author-email: offsetkeyz <pypi@thedailydecrypt.com>
License-Expression: MIT
Project-URL: Homepage, https://github.com/offsetkeyz/dupr-api-client
Project-URL: Documentation, https://github.com/offsetkeyz/dupr-api-client#readme
Project-URL: Repository, https://github.com/offsetkeyz/dupr-api-client
Project-URL: Bug Tracker, https://github.com/offsetkeyz/dupr-api-client/issues
Keywords: dupr,pickleball,rating,api,client
Classifier: Development Status :: 4 - Beta
Classifier: Intended Audience :: Developers
Classifier: Programming Language :: Python :: 3
Classifier: Programming Language :: Python :: 3.8
Classifier: Programming Language :: Python :: 3.9
Classifier: Programming Language :: Python :: 3.10
Classifier: Programming Language :: Python :: 3.11
Classifier: Programming Language :: Python :: 3.12
Classifier: Topic :: Software Development :: Libraries :: Python Modules
Classifier: Topic :: Internet :: WWW/HTTP :: Dynamic Content
Requires-Python: >=3.8
License-File: LICENSE
Requires-Dist: requests>=2.31.0
Provides-Extra: dev
Requires-Dist: pytest>=7.4.0; extra == "dev"
Requires-Dist: pytest-cov>=4.1.0; extra == "dev"
Requires-Dist: responses>=0.23.0; extra == "dev"
Requires-Dist: black>=23.7.0; extra == "dev"
Requires-Dist: mypy>=1.5.0; extra == "dev"
Requires-Dist: flake8>=6.1.0; extra == "dev"
Requires-Dist: types-requests>=2.31.0; extra == "dev"
Dynamic: author
Dynamic: home-page
Dynamic: license-file
Dynamic: requires-python
